datastructures/__init__.py
datastructures/helpers.py
datastructures/structures.c
datastructures/structures.cpython-35m-darwin.so
datastructures/structures.pyx
datastructures-0.1.0.dist-info/DESCRIPTION.rst
datastructures-0.1.0.dist-info/LICENSE.txt
datastructures-0.1.0.dist-info/METADATA
datastructures-0.1.0.dist-info/RECORD
datastructures-0.1.0.dist-info/WHEEL
datastructures-0.1.0.dist-info/metadata.json
datastructures-0.1.0.dist-info/top_level.txt
