Metadata-Version: 2.0
Name: datastructures
Version: 0.1.0
Summary: UNKNOWN
Home-page: https://github.com/quantmind/datastructures
Author: Luca Sbardella
Author-email: luca@quantmind.com
License: BSD
Platform: UNKNOWN
